npDoseResponse/__init__.py
npDoseResponse/npDoseResponse.py
npDoseResponse/npDoseResponseDR.py
npDoseResponse/npDoseResponseDerivDR.py
npDoseResponse/rbf.py
npDoseResponse/utils.py
npDoseResponse-0.0.10.dist-info/LICENSE
npDoseResponse-0.0.10.dist-info/METADATA
npDoseResponse-0.0.10.dist-info/WHEEL
npDoseResponse-0.0.10.dist-info/top_level.txt
npDoseResponse-0.0.10.dist-info/RECORD
