Metadata-Version: 2.1
Name: npDoseResponse
Version: 0.0.10
Summary: Nonparametric Inference on Dose-Response Curve and its Derivative: With and Without Positivity
Home-page: https://github.com/zhangyk8/npDoseResponse
Author: Yikun Zhang
Author-email: yikunzhang@foxmail.com
Classifier: Programming Language :: Python :: 3
Classifier: License :: OSI Approved :: MIT License
Classifier: Operating System :: OS Independent
Requires-Python: >=3.8
License-File: LICENSE
Requires-Dist: numpy>=1.16
Requires-Dist: scipy
Requires-Dist: scikit-learn
Requires-Dist: torch
